data_nut_squirrel/__init__.py
data_nut_squirrel/make_single_api_file.py
data_nut_squirrel/config/__init__.py
data_nut_squirrel/config/dynamic_data_nut.py
data_nut_squirrel/config/nut_data_manager.py
data_nut_squirrel/config/nut_filter_definitions.py
data_nut_squirrel/config/nut_python_build.py
data_nut_squirrel/config/nut_yaml_objects.py
data_nut_squirrel/config/nut_yaml_operations.py
data_nut_squirrel/test/__init__.py
data_nut_squirrel/test/bin/__init__.py
data_nut_squirrel/test/bin/built_api.py
data_nut_squirrel/test/bin/built_config.py
data_nut_squirrel/test/bin/built_single_api_2.py
data_nut_squirrel/test/bin/data/__init__.py
data_nut_squirrel/test/bin/data/demo_external_class.py
data_nut_squirrel/test/data_manager/__init__.py
data_nut_squirrel/test/integration_tests/__init__.py
data_nut_squirrel/test/integration_tests/hold_test_nut_filter_definitions.py
data_nut_squirrel/test/integration_tests/test_new_nut_yaml.py
data_nut_squirrel/test/integration_tests/test_new_python_build.py
data_nut_squirrel/test/integration_tests/test_nut_rna_strand.py
data_nut_squirrel/test/nut_yaml_objects/__init__.py
data_nut_squirrel-2.1.1.0.dist-info/licenses/LICENSE
data_nut_squirrel-2.1.1.0.dist-info/METADATA
data_nut_squirrel-2.1.1.0.dist-info/WHEEL
data_nut_squirrel-2.1.1.0.dist-info/entry_points.txt
data_nut_squirrel-2.1.1.0.dist-info/top_level.txt
data_nut_squirrel-2.1.1.0.dist-info/RECORD
