Metadata-Version: 2.4
Name: data_nut_squirrel
Version: 2.1.1.0
Summary: Wrapper around serialization and provides strict data typing when using type hints
Author-email: Jennifer Pearl <jenpearl5@gmail.com>
License:                     GNU GENERAL PUBLIC LICENSE
Project-URL: Documentation, https://docs.google.com/document/d/1FRSHdIqurGtHC8vD-rI5Ryw-NAj9xbYtGOq5UFW55iU/edit
Project-URL: Repository, https://github.com/LunarFawn/rna_squirrel.git
Classifier: Programming Language :: Python
Classifier: Programming Language :: Python :: 3
Requires-Python: >3.0
License-File: LICENSE
Requires-Dist: ruamel.yaml
Requires-Dist: attrs
Requires-Dist: pytest
Requires-Dist: pathvalidate
Dynamic: license-file
